archijson/__init__.py
archijson/archijson.py
archijson/archiserver.py
archijson/helper.py
archijson/converter/__init__.py
archijson/converter/compas.py
archijson/converter/trimesh.py
archijson/geometry/__init__.py
archijson/geometry/base.py
archijson/geometry/mesh.py
archijson/geometry/shape.py
archijson-0.1.3.dist-info/METADATA
archijson-0.1.3.dist-info/WHEEL
archijson-0.1.3.dist-info/top_level.txt
archijson-0.1.3.dist-info/RECORD
