Metadata-Version: 2.4
Name: archijson
Version: 0.1.3
Summary: ArchiJSON: A Light Weight Web Data Exchange Format for Architectrual Design
Home-page: https://github.com/Inst-AAA/archijson
Author: Yichen Mo
Author-email: moyichen@seu.edu.cn
License: GNU General Public License v3.0
Project-URL: ArchiWeb, https://web.archialgo.com
Project-URL: Documentation, https://docs.web.archialgo.com
Project-URL: Issues, https://github.com/Inst-AAA/archijson/issues
Project-URL: Repository, https://github.com/Inst-AAA/archijson
Keywords: architecture,engineering,design,json,exchange format
Classifier: Development Status :: 3 - Alpha
Classifier: Intended Audience :: Science/Research
Classifier: Topic :: Scientific/Engineering
Classifier: License :: OSI Approved :: GNU General Public License v3 (GPLv3)
Classifier: Programming Language :: Python :: 3
Classifier: Operating System :: POSIX :: Linux
Classifier: Operating System :: MacOS :: MacOS X
Classifier: Operating System :: Microsoft :: Windows
Requires-Dist: schema
Requires-Dist: python-socketio
Requires-Dist: requests
Requires-Dist: websocket-client
Requires-Dist: trimesh
Requires-Dist: mapbox-earcut
Requires-Dist: numpy
Dynamic: author
Dynamic: author-email
Dynamic: classifier
Dynamic: description
Dynamic: description-content-type
Dynamic: home-page
Dynamic: keywords
Dynamic: license
Dynamic: project-url
Dynamic: requires-dist
Dynamic: summary
